infinium/__init__.py
infinium/async_client.py
infinium/client.py
infinium/exceptions.py
infinium/types.py
infinium/utils.py
infinium_o2-1.0.0.dist-info/METADATA
infinium_o2-1.0.0.dist-info/WHEEL
infinium_o2-1.0.0.dist-info/licenses/LICENSE
infinium_o2-1.0.0.dist-info/RECORD
