Metadata-Version: 2.4
Name: infinium-o2
Version: 1.0.0
Summary: Professional Python SDK for Infinium API
Project-URL: Homepage, https://github.com/xyendigital/infinium-python-sdk
Project-URL: Documentation, https://github.com/xyendigital/infinium-python-sdk#readme
Project-URL: Repository, https://github.com/xyendigital/infinium-python-sdk
Project-URL: Bug Tracker, https://github.com/xyendigital/infinium-python-sdk/issues
Project-URL: Changelog, https://github.com/xyendigital/infinium-python-sdk/blob/main/CHANGELOG.md
Author-email: Infinium <support@i42m.ai>
Maintainer-email: Infinium <support@i42m.ai>
License: MIT
License-File: LICENSE
Keywords: agent,api,automation,client,infinium,sdk
Classifier: Development Status :: 5 - Production/Stable
Classifier: Intended Audience :: Developers
Classifier: License :: OSI Approved :: MIT License
Classifier: Operating System :: OS Independent
Classifier: Programming Language :: Python :: 3
Classifier: Programming Language :: Python :: 3.9
Classifier: Programming Language :: Python :: 3.10
Classifier: Programming Language :: Python :: 3.11
Classifier: Programming Language :: Python :: 3.12
Classifier: Topic :: Internet :: WWW/HTTP :: HTTP Servers
Classifier: Topic :: Software Development :: Libraries :: Python Modules
Classifier: Topic :: System :: Networking
Requires-Python: >=3.9
Requires-Dist: httpx>=0.25.0
Requires-Dist: typing-extensions>=4.8.0; python_version < '3.12'
Provides-Extra: dev
Requires-Dist: black>=23.7.0; extra == 'dev'
Requires-Dist: flake8>=6.0.0; extra == 'dev'
Requires-Dist: isort>=5.12.0; extra == 'dev'
Requires-Dist: mypy>=1.5.0; extra == 'dev'
Requires-Dist: pre-commit>=3.3.0; extra == 'dev'
Requires-Dist: pytest-asyncio>=0.21.0; extra == 'dev'
Requires-Dist: pytest-cov>=4.1.0; extra == 'dev'
Requires-Dist: pytest-mock>=3.11.0; extra == 'dev'
Requires-Dist: pytest>=7.4.0; extra == 'dev'
Provides-Extra: examples
Requires-Dist: python-dotenv>=1.0.0; extra == 'examples'
